st_newsapi_connector/__init__.py
st_newsapi_connector/connection.py
st_newsapi_connector-0.1.18.dist-info/LICENSE
st_newsapi_connector-0.1.18.dist-info/WHEEL
st_newsapi_connector-0.1.18.dist-info/METADATA
st_newsapi_connector-0.1.18.dist-info/RECORD
